frame_msg/__init__.py
frame_msg/frame_msg.py
frame_msg/rx_audio.py
frame_msg/rx_auto_exp_result.py
frame_msg/rx_imu.py
frame_msg/rx_metering_data.py
frame_msg/rx_photo.py
frame_msg/rx_tap.py
frame_msg/tx_auto_exp_settings.py
frame_msg/tx_capture_settings.py
frame_msg/tx_code.py
frame_msg/tx_image_sprite_block.py
frame_msg/tx_manual_exp_settings.py
frame_msg/tx_plain_text.py
frame_msg/tx_sprite.py
frame_msg/tx_sprite_coords.py
frame_msg/tx_text_sprite_block.py
frame_msg/lua/audio.lua
frame_msg/lua/audio.min.lua
frame_msg/lua/battery.lua
frame_msg/lua/battery.min.lua
frame_msg/lua/camera.lua
frame_msg/lua/camera.min.lua
frame_msg/lua/code.lua
frame_msg/lua/code.min.lua
frame_msg/lua/data.lua
frame_msg/lua/data.min.lua
frame_msg/lua/image_sprite_block.lua
frame_msg/lua/image_sprite_block.min.lua
frame_msg/lua/imu.lua
frame_msg/lua/imu.min.lua
frame_msg/lua/plain_text.lua
frame_msg/lua/plain_text.min.lua
frame_msg/lua/sprite.lua
frame_msg/lua/sprite.min.lua
frame_msg/lua/sprite_coords.lua
frame_msg/lua/sprite_coords.min.lua
frame_msg/lua/tap.lua
frame_msg/lua/tap.min.lua
frame_msg/lua/text_sprite_block.lua
frame_msg/lua/text_sprite_block.min.lua
frame_msg-5.2.1.dist-info/METADATA
frame_msg-5.2.1.dist-info/WHEEL
frame_msg-5.2.1.dist-info/licenses/LICENSE
frame_msg-5.2.1.dist-info/RECORD
