Metadata-Version: 2.4
Name: frame-msg
Version: 5.2.1
Summary: Handles various message types for the Brilliant Labs Frame
Project-URL: Homepage, https://github.com/CitizenOneX/frame_msg_python
Project-URL: Documentation, https://frame-msg-python.readthedocs.io/en/latest/index.html
Project-URL: Bug Tracker, https://github.com/CitizenOneX/frame_msg_python/issues
Project-URL: Changelog, https://github.com/CitizenOneX/frame_msg_python/blob/main/CHANGELOG.md
Author: CitizenOne
License-File: LICENSE
Classifier: License :: OSI Approved :: BSD License
Classifier: Operating System :: OS Independent
Classifier: Programming Language :: Python :: 3
Requires-Python: >=3.10
Requires-Dist: frame-ble>=1.0.5
Requires-Dist: lz4<5.0.0,>=4.4.3
Requires-Dist: numpy<3.0.0,>=2.2.3
Requires-Dist: pillow<12.0.0,>=11.1.0
